{
    "Walker": {
        "checkpoints": [
            {
                "steps": 9944,
                "file_path": "results\\trial14\\Walker\\Walker-9944.nn",
                "reward": -74.68620610237122,
                "creation_time": 1607273149.145357
            }
        ],
        "final_checkpoint": {
            "steps": 9944,
            "file_path": "results\\trial14\\Walker.nn",
            "reward": -74.68620610237122,
            "creation_time": 1607273149.145357
        }
    },
    "metadata": {
        "stats_format_version": "0.1.0",
        "mlagents_version": "0.21.0",
        "tensorflow_version": "2.3.1"
    }
}